code_check/__init__.py
code_check/cli.py
code_check/code_check.py
code_check-0.1.0.dist-info/AUTHORS.rst
code_check-0.1.0.dist-info/LICENSE
code_check-0.1.0.dist-info/METADATA
code_check-0.1.0.dist-info/WHEEL
code_check-0.1.0.dist-info/entry_points.txt
code_check-0.1.0.dist-info/top_level.txt
code_check-0.1.0.dist-info/RECORD
