Metadata-Version: 2.1
Name: code-check
Version: 0.1.0
Summary: check python code
Home-page: https://github.com/taceywong/code_check
Author: Tacey Wong
Author-email: xinyong.wang@qq.com
License: MIT license
Keywords: code_check
Platform: UNKNOWN
Classifier: Development Status :: 2 - Pre-Alpha
Classifier: Intended Audience :: Developers
Classifier: License :: OSI Approved :: MIT License
Classifier: Natural Language :: English
Classifier: Programming Language :: Python :: 3
Classifier: Programming Language :: Python :: 3.5
Classifier: Programming Language :: Python :: 3.6
Classifier: Programming Language :: Python :: 3.7
Classifier: Programming Language :: Python :: 3.8
Requires-Python: >=3.5
Requires-Dist: Click (>=7.0)
